Metadata-Version: 2.1
Name: valipy
Version: 0.2.3
Summary: A chainable, fluent Python library for validating data
Home-page: https://github.com/pimepan/valipy
Author: Joaquin Jose Von Chong
Author-email: jjvonchong@outlook.com
License: MIT
Keywords: validation,data,schema,schema validation,regex,patter matching
Classifier: Development Status :: 4 - Beta
Classifier: Intended Audience :: Developers
Classifier: Topic :: Software Development
Classifier: License :: OSI Approved :: MIT License
Classifier: Programming Language :: Python :: 3.11
Classifier: Programming Language :: Python :: 3.12
